setup.py
distributionsss/Binomialdistribution.py
distributionsss/Gaussiandistribution.py
distributionsss/Generaldistribution.py
distributionsss/__init__.py
distributionsss.egg-info/PKG-INFO
distributionsss.egg-info/SOURCES.txt
distributionsss.egg-info/dependency_links.txt
distributionsss.egg-info/not-zip-safe
distributionsss.egg-info/top_level.txt